shuaifu.py
shuaifu-1.4.0.data/scripts/shuaifu.py
shuaifu-1.4.0.dist-info/LICENSE
shuaifu-1.4.0.dist-info/METADATA
shuaifu-1.4.0.dist-info/WHEEL
shuaifu-1.4.0.dist-info/top_level.txt
shuaifu-1.4.0.dist-info/RECORD
